{
  "submittedAt": "2025-03-01T09:00:00",
  "campaignID": "domination-20250301090000",
  "productType": "Domination",
  "campaignName": "Woolworths Fresh",
  "location": "AU",
  "clientLogoURL": "https://upload.wikimedia.org/wikipedia/commons/thumb/b/b3/Woolworths_logo.svg/2560px-Woolworths_logo.svg.png",
  "claimText": "Fresh Food People",
  "templateType": "carousel",
  "buttonText": "Discover More",
  "globalBkgType": "color",
  "globalBkgColor": "#00853F",
  "globalBkgTop": "",
  "globalBkgBottom": "",
  "globalTextColor": "#FFFFFF",
  "buttonBkgColor": "#00853F",
  "buttonTextColor": "#FFFFFF",
  "paginationBkgColor": "#AAAAAA",
  "paginationActiveColor": "#00853F",
  "Img01URL": "https://images.unsplash.com/photo-1542838132-92c53300491e?w=800",
  "Img02URL": "https://images.unsplash.com/photo-1490818387583-1baba5e638af?w=800",
  "Img03URL": "https://images.unsplash.com/photo-1610832958506-aa56368176cf?w=800",
  "Img04URL": "https://images.unsplash.com/photo-1606914501449-5a96b6ce24ca?w=800",
  "Img05URL": "",
  "Img06URL": "",
  "ghostoverURL": ""
}